{
  "current": {
    "sections": {
      "announcement-bar": {
        "type": "announcement-bar",
        "blocks": {
          "62fae789-cd01-4a40-975b-191b33200daa": {
            "type": "announcement",
            "settings": {
              "text": "Welcome to our store",
              "color_scheme": "inverse",
              "link": ""
            }
          }
        },
        "block_order": [
          "62fae789-cd01-4a40-975b-191b33200daa"
        ],
        "settings": {
        }
      },
      "header": {
        "type": "header",
        "settings": {
          "logo": "shopify:\/\/shop_images\/NightSwim_Primary.png",
          "logo_width": 100,
          "logo_position": "top-center",
          "menu": "main-menu",
          "show_line_separator": false,
          "enable_sticky_header": true
        }
      },
      "footer": {
        "type": "footer",
        "blocks": {
          "footer-0": {
            "type": "link_list",
            "settings": {
              "heading": "Quick links",
              "menu": "footer"
            }
          },
          "footer-1": {
            "type": "text",
            "settings": {
              "heading": "Heading",
              "subtext": "<p>Share store details, promotions, or brand content with your customers.<\/p>"
            }
          }
        },
        "block_order": [
          "footer-0",
          "footer-1"
        ],
        "settings": {
          "color_scheme": "background-1",
          "newsletter_enable": true,
          "newsletter_heading": "Subscribe to our emails",
          "show_social": false,
          "enable_country_selector": true,
          "enable_language_selector": true,
          "payment_enable": true
        }
      }
    },
    "content_for_index": [

    ]
  }
}
